[
    {
      "displayName": "Any region",
      "value": ""
    },
    {
      "displayName": "Global",
      "value": "Global"
    },
    {
      "displayName": "United States",
      "value": "United States"
    },
    {
      "displayName": "Andorra",
      "value": "Andorra"
    },
    {
      "displayName": "Argentina",
      "value": "Argentina"
    },
    {
      "displayName": "Australia",
      "value": "Australia"
    },
    {
      "displayName": "Austria",
      "value": "Austria"
    },
    {
      "displayName": "Belgium",
      "value": "Belgium"
    },
    {
      "displayName": "Bolivia",
      "value": "Bolivia"
    },
    {
      "displayName": "Brazil",
      "value": "Brazil"
    },
    {
      "displayName": "Bulgaria",
      "value": "Bulgaria"
    },
    {
      "displayName": "Canada",
      "value": "Canada"
    },
    {
      "displayName": "Chile",
      "value": "Chile"
    },
    {
      "displayName": "Colombia",
      "value": "Colombia"
    },
    {
      "displayName": "Costa Rica",
      "value": "Costa Rica"
    },
    {
      "displayName": "Czech Republic",
      "value": "Czech Republic"
    },
    {
      "displayName": "Denmark",
      "value": "Denmark"
    },
    {
      "displayName": "Dominican Republic",
      "value": "Dominican Republic"
    },
    {
      "displayName": "Ecuador",
      "value": "Ecuador"
    },
    {
      "displayName": "Egypt",
      "value": "Egypt"
    },
    {
      "displayName": "El Salvador",
      "value": "El Salvador"
    },
    {
      "displayName": "Estonia",
      "value": "Estonia"
    },
    {
      "displayName": "Finland",
      "value": "Finland"
    },
    {
      "displayName": "France",
      "value": "France"
    },
    {
      "displayName": "Germany",
      "value": "Germany"
    },
    {
      "displayName": "Greece",
      "value": "Greece"
    },
    {
      "displayName": "Guatemala",
      "value": "Guatemala"
    },
    {
      "displayName": "Honduras",
      "value": "Honduras"
    },
    {
      "displayName": "Hong Kong",
      "value": "Hong Kong"
    },
    {
      "displayName": "Hungary",
      "value": "Hungary"
    },
    {
      "displayName": "Iceland",
      "value": "Iceland"
    },
    {
      "displayName": "India",
      "value": "India"
    },
    {
      "displayName": "Indonesia",
      "value": "Indonesia"
    },
    {
      "displayName": "Ireland",
      "value": "Ireland"
    },
    {
      "displayName": "Israel",
      "value": "Israel"
    },
    {
      "displayName": "Italy",
      "value": "Italy"
    },
    {
      "displayName": "Japan",
      "value": "Japan"
    },
    {
      "displayName": "Latvia",
      "value": "Latvia"
    },
    {
      "displayName": "Lithuania",
      "value": "Lithuania"
    },
    {
      "displayName": "Luxembourg",
      "value": "Luxembourg"
    },
    {
      "displayName": "Malaysia",
      "value": "Malaysia"
    },
    {
      "displayName": "Mexico",
      "value": "Mexico"
    },
    {
      "displayName": "Morocco",
      "value": "Morocco"
    },
    {
      "displayName": "Netherlands",
      "value": "Netherlands"
    },
    {
      "displayName": "New Zealand",
      "value": "New Zealand"
    },
    {
      "displayName": "Sweden",
      "value": "Sweden"
    },
    {
      "displayName": "Nicaragua",
      "value": "Nicaragua"
    },
    {
      "displayName": "Norway",
      "value": "Norway"
    },
    {
      "displayName": "Portugal",
      "value": "Portugal"
    },
    {
      "displayName": "Panama",
      "value": "Panama"
    },
    {
      "displayName": "Paraguay",
      "value": "Paraguay"
    },
    {
      "displayName": "Peru",
      "value": "Peru"
    },
    {
      "displayName": "Philippines",
      "value": "Philippines"
    },
    {
      "displayName": "Poland",
      "value": "Poland"
    },
    {
      "displayName": "Singapore",
      "value": "Singapore"
    },
    {
      "displayName": "Slovakia",
      "value": "Slovakia"
    },
    {
      "displayName": "Spain",
      "value": "Spain"
    },
    {
      "displayName": "Switzerland",
      "value": "Switzerland"
    },
    {
      "displayName": "Taiwan",
      "value": "Taiwan"
    },
    {
      "displayName": "Thailand",
      "value": "Thailand"
    },
    {
      "displayName": "Turkey",
      "value": "Turkey"
    },
    {
      "displayName": "United Kingdom",
      "value": "United Kingdom"
    },
    {
      "displayName": "Uruguay",
      "value": "Uruguay"
    }
  ]